loralib/__init__.py
loralib/layers.py
loralib/utils.py
mup-0.0.0.dist-info/METADATA
mup-0.0.0.dist-info/WHEEL
mup-0.0.0.dist-info/top_level.txt
mup-0.0.0.dist-info/RECORD
