Metadata-Version: 2.1
Name: mup
Version: 0.0.0
Summary: UNKNOWN
Home-page: https://github.com/microsoft/mup
Author: GYAIL
Author-email: edward.hu@microsoft.com
License: UNKNOWN
Platform: UNKNOWN
Classifier: Programming Language :: Python :: 3
Classifier: License :: OSI Approved :: MIT License
Classifier: Operating System :: OS Independent
Requires-Python: >=3.6
